LICENSE
MANIFEST.in
README.md
setup.py
bicon/__init__.py
bicon/ants.py
bicon/load_data.py
bicon/results_processing.py
bicon.egg-info/PKG-INFO
bicon.egg-info/SOURCES.txt
bicon.egg-info/dependency_links.txt
bicon.egg-info/requires.txt
bicon.egg-info/top_level.txt