Metadata-Version: 2.1
Name: bicon
Version: 1.3.3
Summary: BiCoN - a package for network-constrained biclustering of omics data
Home-page: https://github.com/biomedbigdata/BiCoN
Author: Olga Lazareva
Author-email: olga.lazareva@tum.de
License: UNKNOWN
Platform: UNKNOWN
Classifier: Programming Language :: Python :: 3
Classifier: License :: OSI Approved :: GNU General Public License v3 (GPLv3)
Classifier: Operating System :: OS Independent
Requires-Python: >=3.8
License-File: LICENSE
